{"authorDailyContributionsMap":{"michael-lee-sk":[{"date":"2021-09-26","commitResults":[{"hash":"c92f5baf6a741e1bff78465bd57e2d0668ca39b3","messageTitle":"Update DeveloperGuide","messageBody":"Updated - Product scope / User stories / NFRs\r\n\r\nOutstanding: Use cases","fileTypesAndContributionMap":{"docs":{"insertions":46,"deletions":24}}},{"hash":"9ce20158fdf4c5d55f9952114b177255396d7dc3","messageTitle":"Add Enroll/Unenroll Use Cases","messageBody":"","fileTypesAndContributionMap":{"docs":{"insertions":30,"deletions":12}}}]},{"date":"2021-09-28","commitResults":[{"hash":"ce913c435e1f58f547fe4cc4feda6d691c458b67","messageTitle":"Update UserGuide","messageBody":"","fileTypesAndContributionMap":{"docs":{"insertions":5,"deletions":5}}},{"hash":"d2b22773ddf940db2c44f23c315bea6db5e1005b","messageTitle":"Update DevGuide","messageBody":"","fileTypesAndContributionMap":{"docs":{"insertions":2,"deletions":2}}}]}],"eezj35":[{"date":"2021-09-20","commitResults":[{"hash":"6e8a7370cd197348c2043dfe835364fbeeee2439","messageTitle":"Update README.md","messageBody":"","fileTypesAndContributionMap":{"docs":{"insertions":14,"deletions":11}}},{"hash":"7f401da715bb3cf85ee27225ac0305ae39ab6da8","messageTitle":"Update index.md","messageBody":"","fileTypesAndContributionMap":{"docs":{"insertions":1,"deletions":1}}},{"hash":"5d17b30879eb6f4809457e1095bf967bb93df7db","messageTitle":"Change website title","messageBody":"","fileTypesAndContributionMap":{"docs":{"insertions":1,"deletions":1}}}]},{"date":"2021-09-21","commitResults":[{"hash":"294d7ad9279a6d68e95ec08d24d76238f1082e6a","messageTitle":"Add Grade class","messageBody":"","fileTypesAndContributionMap":{"functional-code":{"insertions":74,"deletions":0}}},{"hash":"fff38a49fcd07d3064221387fa9127ec403b860e","messageTitle":"Fix checkstyle issues","messageBody":"","fileTypesAndContributionMap":{"functional-code":{"insertions":7,"deletions":6}}},{"hash":"f648405bb9ed1bf298e8b730d5510733143bee5e","messageTitle":"Add constructor documentation","messageBody":"","fileTypesAndContributionMap":{"functional-code":{"insertions":6,"deletions":2}}}]},{"date":"2021-09-26","commitResults":[{"hash":"39445c80672f89f4c4c2fd515b400471bd3c90dd","messageTitle":"Add \"look up student details\" use case","messageBody":"","fileTypesAndContributionMap":{"docs":{"insertions":33,"deletions":9}}}]}],"MGRL2201":[{"date":"2021-09-20","commitResults":[{"hash":"d7ddd270c2a85c07ddde655f575189be7160df0f","messageTitle":"update user guide","messageBody":"","fileTypesAndContributionMap":{"docs":{"insertions":63,"deletions":61}}},{"hash":"df2a24db6362ab400b63bd14bbfb9fa924594e6e","messageTitle":"more updates to user guide","messageBody":"","fileTypesAndContributionMap":{"docs":{"insertions":4,"deletions":3}}},{"hash":"ca4660827150a3eaf36c6d19ca1eeef24ebf5442","messageTitle":"Update UserGuide.md","messageBody":"","fileTypesAndContributionMap":{"docs":{"insertions":0,"deletions":1}}}]},{"date":"2021-09-26","commitResults":[{"hash":"bfb480db8233fca312cba3dadfae9d15ef926344","messageTitle":"add use case for add/delete student","messageBody":"","fileTypesAndContributionMap":{"docs":{"insertions":34,"deletions":8}}}]}],"Timothyoung97":[{"date":"2021-09-20","commitResults":[{"hash":"21aac21b360be47c634becd926d7233470db5ec1","messageTitle":"Change Ui.png to mock up version","messageBody":"","fileTypesAndContributionMap":{"functional-code":{"insertions":1,"deletions":1}}},{"hash":"a4ab0e1cf3f89429974e9a1f67318e7ccea548d5","messageTitle":"Change Project Page to TutiONE","messageBody":"","fileTypesAndContributionMap":{"docs":{"insertions":6,"deletions":4}}}]},{"date":"2021-09-26","commitResults":[{"hash":"ef549b2ae281460e1dc40ce97d9bf3da0920bcbe","messageTitle":"Update DG UC: Update a specific student\u0027s details","messageBody":"","fileTypesAndContributionMap":{"docs":{"insertions":19,"deletions":0}}},{"hash":"824a45f932a8e9b966708980e23160a5bbe62aee","messageTitle":"Update on Use Case: Update Student\u0027s Details","messageBody":"","fileTypesAndContributionMap":{"docs":{"insertions":9,"deletions":8}}},{"hash":"4c414c022009690641c660f53881e369727271c6","messageTitle":"Edit on UC format","messageBody":"","fileTypesAndContributionMap":{"docs":{"insertions":22,"deletions":12}}}]}],"muhammad-khair":[{"date":"2021-09-20","commitResults":[{"hash":"1927a4924c1bde51e3a5ad6ee3c9075fc2e625c8","messageTitle":"Update docs/AboutUs.md","messageBody":"","fileTypesAndContributionMap":{"docs":{"insertions":26,"deletions":28}}},{"hash":"37a06cda0171fc5106ccb48cf6874015489180d2","messageTitle":"Add portfolios for team members","messageBody":"","fileTypesAndContributionMap":{"docs":{"insertions":191,"deletions":2}}}]},{"date":"2021-09-21","commitResults":[{"hash":"c079766a001fa71ac1c6cb4560c9a334fb2a5f4b","messageTitle":"Docs: rename class to lesson","messageBody":"","fileTypesAndContributionMap":{"docs":{"insertions":19,"deletions":19}}},{"hash":"5c8977f783759fa49d7520fb3787a21bb1f1abf9","messageTitle":"Add base Lesson entity","messageBody":"","fileTypesAndContributionMap":{"functional-code":{"insertions":132,"deletions":0}}},{"hash":"128d88e589289e0281ecb82e0f3b04a0840e5f48","messageTitle":"Update logic for Lesson constraints","messageBody":"","fileTypesAndContributionMap":{"functional-code":{"insertions":12,"deletions":17}}}]},{"date":"2021-09-23","commitResults":[{"hash":"887b44a9e1b513c685fa793c0e1e1bbc4cd8a949","messageTitle":"Add price field in Lesson","messageBody":"","fileTypesAndContributionMap":{"functional-code":{"insertions":4,"deletions":2}}},{"hash":"ab3129e8b70ca896687b3354fe092d7e99375a21","messageTitle":"Change fields from public to private","messageBody":"","fileTypesAndContributionMap":{"functional-code":{"insertions":43,"deletions":12}}},{"hash":"e5ff8d0ad80fbf81589e2e5f4cf2e7976b3dc054","messageTitle":"Add price constraint in Lesson","messageBody":"","fileTypesAndContributionMap":{"functional-code":{"insertions":9,"deletions":0}}},{"hash":"9e79e190d44f5670c84b4367e02cfbd7f341b1e1","messageTitle":"Update UserGuide.md","messageBody":"","fileTypesAndContributionMap":{"docs":{"insertions":10,"deletions":9}}},{"hash":"13820bd357040e356733dad28e681ce9186bbc0c","messageTitle":"Update Lesson to hold DayOfWeek instead of LocalDate","messageBody":"","fileTypesAndContributionMap":{"functional-code":{"insertions":37,"deletions":44},"docs":{"insertions":1,"deletions":1}}},{"hash":"4185d9a86b8a2afe14afdcf7a3cb88a2eac905d6","messageTitle":"Update UserGuide.md","messageBody":"","fileTypesAndContributionMap":{"docs":{"insertions":4,"deletions":3}}},{"hash":"a2a8e7d91c0b5dfec23ce9cc60c7aae7ab7ca100","messageTitle":"DG: add lesson-related use cases","messageBody":"","fileTypesAndContributionMap":{"docs":{"insertions":63,"deletions":8}}},{"hash":"a727e06d0745a0410bba34cd9d8dcd21ba73b0e5","messageTitle":"Update command summary in UserGuide.md","messageBody":"","fileTypesAndContributionMap":{"docs":{"insertions":3,"deletions":3}}}]},{"date":"2021-09-26","commitResults":[{"hash":"87c05cd22730af47f2238d5f95046fb2d037292a","messageTitle":"Remove getLessonSize method","messageBody":"","fileTypesAndContributionMap":{"functional-code":{"insertions":0,"deletions":7}}}]}]},"authorFileTypeContributionMap":{"michael-lee-sk":{"docs":44,"functional-code":0,"test-code":0},"eezj35":{"docs":19,"functional-code":79,"test-code":0,"other":1},"MGRL2201":{"docs":63,"functional-code":0,"test-code":0},"Timothyoung97":{"docs":124,"functional-code":1,"test-code":0},"muhammad-khair":{"docs":85,"functional-code":155,"test-code":0}},"authorContributionVariance":{"michael-lee-sk":951.4167,"eezj35":777.80566,"MGRL2201":1388.75,"Timothyoung97":373.6389,"muhammad-khair":10358.744},"authorDisplayNameMap":{"michael-lee-sk":"CS2103T-F13-4 MICH..KIAT","eezj35":"CS2103T-F13-4 EE Z..STIN","MGRL2201":"CS2103T-F13-4 LI M..CKIE","Timothyoung97":"CS2103T-F13-4 YANG..YUAN","muhammad-khair":"CS2103T-F13-4 MUHA..SHID"}}
