{"authorDailyContributionsMap":{"ngsengleng":[{"date":"2021-09-23","commitResults":[{"hash":"353de9bb9197b9c3fd839d22ba00c0f83b3c0a7d","messageTitle":"Add Seng Leng portfolio and image","messageBody":"","fileTypesAndContributionMap":{"docs":{"insertions":15,"deletions":3}}},{"hash":"69f35aec0efa9ebceaba47a7c88e8166ba3bfcd5","messageTitle":"Update AboutUs.md","messageBody":"","fileTypesAndContributionMap":{"docs":{"insertions":1,"deletions":1}}}]},{"date":"2021-09-26","commitResults":[{"hash":"302fd6a3f144ab8c2ca155029330bec1eb8fbffb","messageTitle":"Modify user guide to include suggestions and help, fix table formatting for summary","messageBody":"","fileTypesAndContributionMap":{"docs":{"insertions":13,"deletions":14}}}]}],"radiankrisno":[{"date":"2021-09-22","commitResults":[{"hash":"28766b6d9896b5019143b80d139f944db231e359","messageTitle":"Update AboutUs with radiankrisno information","messageBody":"","fileTypesAndContributionMap":{"docs":{"insertions":18,"deletions":6}}},{"hash":"5dcaff8169670622b7eb4349f4feabcb6572995e","messageTitle":"Update readme","messageBody":"","fileTypesAndContributionMap":{"docs":{"insertions":14,"deletions":11}}},{"hash":"24ba5ea45d7691211edd983feba5260d489ff2b3","messageTitle":"Remove trailing whitespace","messageBody":"","fileTypesAndContributionMap":{"docs":{"insertions":3,"deletions":2}}},{"hash":"106f0e194df688894bcb08ba70e42e591b6bb6f1","messageTitle":"Add newline","messageBody":"","fileTypesAndContributionMap":{"docs":{"insertions":0,"deletions":1}}},{"hash":"8b08fa72b4b5ee13c9f862055edd77b0dc56a676","messageTitle":"Repair link","messageBody":"","fileTypesAndContributionMap":{"docs":{"insertions":1,"deletions":1}}}]},{"date":"2021-09-24","commitResults":[{"hash":"84ace924e3b764f386ff9b9b79a18fcd8f586fc7","messageTitle":"Add user guide for patients and doctors CRUD operations","messageBody":"","fileTypesAndContributionMap":{"docs":{"insertions":112,"deletions":74}}}]},{"date":"2021-09-25","commitResults":[{"hash":"1f863044752d632a5fc028c91618241ac74a3c40","messageTitle":"PR Fixes","messageBody":"","fileTypesAndContributionMap":{"docs":{"insertions":40,"deletions":41}}},{"hash":"9fb633a76a56f4efe435a5aa31c07dadb52be7fe","messageTitle":"Add optional flags header","messageBody":"","fileTypesAndContributionMap":{"docs":{"insertions":2,"deletions":0}}},{"hash":"a1feb3d0e243f9f54dfe1566a5aa033fbb9c34d4","messageTitle":"Update optional flag notation","messageBody":"","fileTypesAndContributionMap":{"docs":{"insertions":2,"deletions":2}}},{"hash":"efece29e674dc6b77f4dc85c47b27794f493f928","messageTitle":"Change optional_flag to optional_parameter","messageBody":"","fileTypesAndContributionMap":{"docs":{"insertions":2,"deletions":2}}}]}],"ramaven":[{"date":"2021-09-27","commitResults":[{"hash":"439ea266e56011d62c9eca222ab709fafe31e3d2","messageTitle":"Update AboutUs.md with Rama\u0027s details","messageBody":"","fileTypesAndContributionMap":{"docs":{"insertions":18,"deletions":4}}},{"hash":"9fae32ac934e4ed0c8a9d2c446d6bcc760f51e3e","messageTitle":"Update UG with list command for patient and doctor","messageBody":"","fileTypesAndContributionMap":{"docs":{"insertions":36,"deletions":0}}},{"hash":"39cf53117f059fa5deae5b09b99de2e0ff139c9c","messageTitle":"Update UG for displaying doctor\u0027s details","messageBody":"","fileTypesAndContributionMap":{"docs":{"insertions":11,"deletions":0}}},{"hash":"0feb2f29643f67abcc8dc39b6e4627683169f4b2","messageTitle":"Update UG to display a patient\u0027s details","messageBody":"","fileTypesAndContributionMap":{"docs":{"insertions":11,"deletions":0}}},{"hash":"7c7efb650a40ef89810e9cdd61ca90faa4517cd4","messageTitle":"Update UG list patients and doctors","messageBody":"","fileTypesAndContributionMap":{"docs":{"insertions":7,"deletions":21}}},{"hash":"982b5faaf2dd4f565450f1cebee86b8513e912ff","messageTitle":"Update UG with uniform list format","messageBody":"","fileTypesAndContributionMap":{"docs":{"insertions":6,"deletions":6}}}]},{"date":"2021-09-28","commitResults":[{"hash":"12b53bba2babb5a339fb90b5fb6dee58c2dfc258","messageTitle":"Change view details to use ID","messageBody":"","fileTypesAndContributionMap":{"docs":{"insertions":8,"deletions":8}}}]},{"date":"2021-09-29","commitResults":[{"hash":"dd1a42921898cb169ae0e4869c9a1225095eebe1","messageTitle":"Add UI mockup for doctors page","messageBody":"","fileTypesAndContributionMap":{"docs":{"insertions":2,"deletions":0}}},{"hash":"db504473a3851d407b0c216596830687f20a96fc","messageTitle":"Add single doctor patient UI; update list UI","messageBody":"","fileTypesAndContributionMap":{"docs":{"insertions":4,"deletions":0}}},{"hash":"320808fb454862dbdd3d53415e082d30b3bb2539","messageTitle":"Add UI for activity page","messageBody":"","fileTypesAndContributionMap":{"docs":{"insertions":2,"deletions":1}}}]}],"simonjulianl":[{"date":"2021-09-22","commitResults":[{"hash":"c28e5cb217e6b2161a44f06087c4d63da7d74ade","messageTitle":"Change pr template and update simon about us","messageBody":"","fileTypesAndContributionMap":{"docs":{"insertions":2,"deletions":0}}},{"hash":"9b6ed2f9de45c3736db4c8931da56ef0ea4dfe91","messageTitle":"Add simon picture and portfolio","messageBody":"","fileTypesAndContributionMap":{"docs":{"insertions":27,"deletions":13}}}]},{"date":"2021-09-24","commitResults":[{"hash":"05a44ff3285ef57c6c706fbfbb22ac9ad684943d","messageTitle":"Update profile pics in correct position due to tracker","messageBody":"","fileTypesAndContributionMap":{"docs":{"insertions":5,"deletions":5}}},{"hash":"34f3f5193b05bc3bc552897854b3a5bc7a98d67c","messageTitle":"Add User stories for DG","messageBody":"","fileTypesAndContributionMap":{"docs":{"insertions":210,"deletions":83}}},{"hash":"6c79c4ef90c0e55b548e4acbf6d3ab87bafaab6e","messageTitle":"Add add, delete and suggestion use cases","messageBody":"","fileTypesAndContributionMap":{"docs":{"insertions":37,"deletions":19}}},{"hash":"3f6622a002299d55a03982f2d0392f14bfd2a89c","messageTitle":"Add NFR and glossary","messageBody":"","fileTypesAndContributionMap":{"docs":{"insertions":20,"deletions":5}}},{"hash":"94c35a462dedbcecf5eaff58d8ba321c2f71531c","messageTitle":"Add user guide for listing activities","messageBody":"","fileTypesAndContributionMap":{"docs":{"insertions":56,"deletions":3}}},{"hash":"42da228f1f59ae07e34887f535669f20a67f7154","messageTitle":"Remove flavoured markdown on line 121","messageBody":"","fileTypesAndContributionMap":{"docs":{"insertions":73,"deletions":47}}},{"hash":"4dddf8d77c294f1fb2c9939d4edbdbbb98bc40a9","messageTitle":"Update the header of DG and UG","messageBody":"","fileTypesAndContributionMap":{"docs":{"insertions":37,"deletions":23}}}]},{"date":"2021-09-28","commitResults":[{"hash":"9d5d6a30ef9784f3c917603e01e32e2c676e80f5","messageTitle":"Change package name from seedu.addressbook to gomedic","messageBody":"","fileTypesAndContributionMap":{"other":{"insertions":809,"deletions":835},"docs":{"insertions":9,"deletions":9},"test-code":{"insertions":360,"deletions":417}}},{"hash":"6f8d87c6488e03579d32d451a09e6f689b4f8dba","messageTitle":"Fix checkstyle","messageBody":"","fileTypesAndContributionMap":{"functional-code":{"insertions":273,"deletions":244},"test-code":{"insertions":20,"deletions":21}}},{"hash":"ec4b6b41bc1fcc1529d7843118f2dde19bc81bf3","messageTitle":"Fix error in valid file with fx root","messageBody":"","fileTypesAndContributionMap":{"test-code":{"insertions":1,"deletions":1}}},{"hash":"580d1c3f632701de94b71a6fa219baee18e44cc2","messageTitle":"Finish checkstyle for test","messageBody":"","fileTypesAndContributionMap":{"test-code":{"insertions":345,"deletions":183}}},{"hash":"b2c8e13644f11778b94b4c17d930d804d1f613a8","messageTitle":"Change link of the UG","messageBody":"","fileTypesAndContributionMap":{"docs":{"insertions":1,"deletions":1}}}]},{"date":"2021-09-29","commitResults":[{"hash":"28be06644c3d70b05c0e4e45b4cb37cfcb6e4ccd","messageTitle":"Update addressbook.jar to gomedic.jar","messageBody":"","fileTypesAndContributionMap":{"other":{"insertions":2,"deletions":2}}},{"hash":"cb18702d280b174b0e0d013d7fbc56a1b7ff7977","messageTitle":"Update DG link to gomedic","messageBody":"","fileTypesAndContributionMap":{"functional-code":{"insertions":1,"deletions":1},"docs":{"insertions":60,"deletions":51}}},{"hash":"eeb31f3563e4f151ac737cbef566bb67fc37a268","messageTitle":"Clean up index.md","messageBody":"","fileTypesAndContributionMap":{"docs":{"insertions":19,"deletions":15}}},{"hash":"ab8a08532fcf70e4036c143361d5bf15581d0b9a","messageTitle":"Fix toc bug","messageBody":"","fileTypesAndContributionMap":{"docs":{"insertions":4,"deletions":2}}},{"hash":"5af337d85684aafb46bfa69b74141bd7f14d4727","messageTitle":"Finalize UG","messageBody":"","fileTypesAndContributionMap":{"docs":{"insertions":109,"deletions":61}}}]},{"date":"2021-09-30","commitResults":[{"hash":"bdc29e446915c550561f9f93141c27cd314a513f","messageTitle":"Update rama link in AboutUs","messageBody":"","fileTypesAndContributionMap":{"docs":{"insertions":1,"deletions":1}}},{"hash":"9ddda9a8e7477fc57e8e192f81754538cfdee46e","messageTitle":"Update docs/UserGuide.md","messageBody":"Co-authored-by: Yuhang \u003c48285332+yyhangz@users.noreply.github.com\u003e","fileTypesAndContributionMap":{"docs":{"insertions":1,"deletions":1}}},{"hash":"d2339063e2e729d9ce2a52bed3d5b1de18c4a4d7","messageTitle":"Update docs/UserGuide.md","messageBody":"Co-authored-by: Yuhang \u003c48285332+yyhangz@users.noreply.github.com\u003e","fileTypesAndContributionMap":{"docs":{"insertions":1,"deletions":1}}}]},{"date":"2021-10-01","commitResults":[{"hash":"4130fcea7a52fd4f2c9927f69877a30ebd193b09","messageTitle":"Add Id class and move classes to common fields","messageBody":"Signed-off-by: Simon Julian Lauw \u003csimonjulianl@u.nus.edu\u003e\n","fileTypesAndContributionMap":{"docs":{"insertions":9,"deletions":14}}},{"hash":"79aad3631a1cdcf6b29c2b940b7ff478e54af20a","messageTitle":"Add Id class and move classes to common fields","messageBody":"Signed-off-by: Simon Julian Lauw \u003csimonjulianl@u.nus.edu\u003e\n","fileTypesAndContributionMap":{"functional-code":{"insertions":27,"deletions":23},"other":{"insertions":13,"deletions":13},"test-code":{"insertions":29,"deletions":29}}},{"hash":"28dc12dffd371c5ee6b4a2f3ad870be8dbf75097","messageTitle":"Add test for Id","messageBody":"Signed-off-by: Simon Julian Lauw \u003csimonjulianl@u.nus.edu\u003e\n","fileTypesAndContributionMap":{"functional-code":{"insertions":64,"deletions":0},"test-code":{"insertions":54,"deletions":0}}},{"hash":"8125c9b2c20a29b0ad6b030455b5badbac0aa0ac","messageTitle":"Add activity id and its test","messageBody":"","fileTypesAndContributionMap":{"functional-code":{"insertions":51,"deletions":5},"test-code":{"insertions":45,"deletions":4}}},{"hash":"605261025d5d2c07b0155e76a674b32c345c7744","messageTitle":"Add more tests to id and activity test","messageBody":"","fileTypesAndContributionMap":{"test-code":{"insertions":40,"deletions":0}}}]},{"date":"2021-10-02","commitResults":[{"hash":"fb15be8e79f21a48940dad2058452b68071d3d82","messageTitle":"Update UG and add more tests for id","messageBody":"","fileTypesAndContributionMap":{"docs":{"insertions":18,"deletions":18}}}]}],"yyhangz":[{"date":"2021-09-23","commitResults":[{"hash":"ffc96dd590c481435739578f31d4c07c013bd40e","messageTitle":"Rename Simon\u0027s developer picture to github username","messageBody":"","fileTypesAndContributionMap":{"docs":{"insertions":1,"deletions":1}}},{"hash":"8f9d1b23f5483133dc5cb65d315f4de382a71231","messageTitle":"Add Yuhang portfolio and image","messageBody":"","fileTypesAndContributionMap":{"docs":{"insertions":13,"deletions":0}}},{"hash":"43601b4cdad22141a8d8bc274be916cffab464aa","messageTitle":"Add Yuhang\u0027s profile in aboutUs","messageBody":"","fileTypesAndContributionMap":{"docs":{"insertions":4,"deletions":4}}}]},{"date":"2021-09-24","commitResults":[{"hash":"15d8c7a4bb6115a2c107b752134d9b69f67075f7","messageTitle":"Add find and tag command specifications to UG","messageBody":"","fileTypesAndContributionMap":{"docs":{"insertions":65,"deletions":4}}},{"hash":"6577277c5f8ae2521db37d957334a76f8cd6608d","messageTitle":"Fix spacing issue of find command in User Guide","messageBody":"","fileTypesAndContributionMap":{"docs":{"insertions":4,"deletions":4}}},{"hash":"0a324dbe2a66a99808f8aa72bd0ba6e082d5a7cb","messageTitle":"Fix typos in find command in User Guide","messageBody":"","fileTypesAndContributionMap":{"docs":{"insertions":3,"deletions":3}}},{"hash":"b2f9eaad5b70180e1edfea77d41838bb1b7985c5","messageTitle":"Fix typos in find command in User Guide","messageBody":"","fileTypesAndContributionMap":{"docs":{"insertions":1,"deletions":1}}}]}]},"authorFileTypeContributionMap":{"ngsengleng":{"docs":18,"functional-code":0,"test-code":0},"radiankrisno":{"docs":103,"functional-code":0,"test-code":0},"ramaven":{"docs":43,"functional-code":0,"test-code":0},"simonjulianl":{"docs":476,"functional-code":644,"test-code":1151,"other":2},"yyhangz":{"docs":64,"functional-code":0,"test-code":0}},"authorContributionVariance":{"ngsengleng":61.933594,"radiankrisno":2447.1094,"ramaven":838.9336,"simonjulianl":723531.4,"yyhangz":439.0625},"authorDisplayNameMap":{"ngsengleng":"CS2103T-T15-1 NG S..LENG","radiankrisno":"CS2103T-T15-1 RADI..ISNO","ramaven":"CS2103T-T15-1 RAMA..TESH","simonjulianl":"CS2103T-T15-1 SIMO..LAUW","yyhangz":"CS2103T-T15-1 YAP ..HANG"}}
